printsafe/__init__.py
printsafe/env.py
printsafe/py.typed
printsafe/secret.py
printsafe-0.2.0.dist-info/METADATA
printsafe-0.2.0.dist-info/WHEEL
printsafe-0.2.0.dist-info/licenses/LICENSE
printsafe-0.2.0.dist-info/RECORD
