Metadata-Version: 2.4
Name: printsafe
Version: 0.2.0
Summary: Python library to keep secrets out of logs
Author-email: Markus Feiks <pypi.packages@feyx.de>
License-File: LICENSE
Requires-Python: >=3.10
